Metadata-Version: 1.0
Name: basicstatistics
Version: 0.1
Summary: Calculate Mean, Median, Mode, Standard Deviation, Gaussian, Binomial and Normal distributions
Home-page: UNKNOWN
Author: UNKNOWN
Author-email: sjahnaviprasad2000@gmail.com
License: UNKNOWN
Platform: UNKNOWN
